{
  "trade_date": "2026-01-16",
  "schema_version": 1,
  "skipped_fetch": [],
  "nifty_spot": 25694.35,
  "nifty_atm_strike": 25700,
  "nifty_max_pain": 25750.0,
  "nifty_max_pain_dev_pct": 0.21658457987846144,
  "nifty_ce_oi_total": 193151530,
  "nifty_pe_oi_total": 125737560,
  "nifty_ce_oi_chg": 48060805,
  "nifty_pe_oi_chg": 27141400,
  "nifty_pcr_oi": 0.6509788454691505,
  "nifty_pcr_vol": 0.9741977306282678,
  "nifty_ce_vol_total": 72939747,
  "nifty_pe_vol_total": 71057736,
  "nifty_atm_ce_oi": 8526700,
  "nifty_atm_pe_oi": 6869135,
  "nifty_max_ce_oi_strike": 26000,
  "nifty_max_pe_oi_strike": 25500,
  "nifty_atm_straddle": 207.1,
  "nifty_front_expiry": "2026-01-20",
  "banknifty_spot": 60095.15,
  "banknifty_atm_strike": 60100,
  "banknifty_max_pain": 59800.0,
  "banknifty_max_pain_dev_pct": -0.4911378039658799,
  "banknifty_ce_oi_total": 14027730,
  "banknifty_pe_oi_total": 14797410,
  "banknifty_ce_oi_chg": 78450,
  "banknifty_pe_oi_chg": 2250060,
  "banknifty_pcr_oi": 1.054868464106452,
  "banknifty_pcr_vol": 0.9546962363113558,
  "banknifty_ce_vol_total": 1779212,
  "banknifty_pe_vol_total": 1698607,
  "banknifty_atm_ce_oi": 423930,
  "banknifty_atm_pe_oi": 279030,
  "banknifty_max_ce_oi_strike": 60000,
  "banknifty_max_pe_oi_strike": 59500,
  "banknifty_atm_straddle": 934.15,
  "banknifty_front_expiry": "2026-01-27",
  "poi_fii_fut_idx_long": 21814,
  "poi_fii_fut_idx_short": 212189,
  "poi_fii_fut_idx_net": -190375,
  "poi_fii_fut_stk_long": 3828614,
  "poi_fii_fut_stk_short": 2394779,
  "poi_fii_fut_stk_net": 1433835,
  "poi_fii_opt_idx_ce_long": 695782,
  "poi_fii_opt_idx_pe_long": 795533,
  "poi_fii_opt_idx_ce_short": 695041,
  "poi_fii_opt_idx_pe_short": 476720,
  "poi_fii_total_long": 5741269,
  "poi_fii_total_short": 4162055,
  "poi_fii_total_net": 1579214,
  "poi_dii_fut_idx_long": 77882,
  "poi_dii_fut_idx_short": 36365,
  "poi_dii_fut_idx_net": 41517,
  "poi_dii_fut_stk_long": 251907,
  "poi_dii_fut_stk_short": 4858241,
  "poi_dii_fut_stk_net": -4606334,
  "poi_dii_opt_idx_ce_long": 2103,
  "poi_dii_opt_idx_pe_long": 38226,
  "poi_dii_opt_idx_ce_short": 0,
  "poi_dii_opt_idx_pe_short": 0,
  "poi_dii_total_long": 394255,
  "poi_dii_total_short": 5298463,
  "poi_dii_total_net": -4904208,
  "poi_client_fut_idx_long": 207613,
  "poi_client_fut_idx_short": 68886,
  "poi_client_fut_idx_net": 138727,
  "poi_client_fut_stk_long": 2990191,
  "poi_client_fut_stk_short": 329786,
  "poi_client_fut_stk_net": 2660405,
  "poi_client_opt_idx_ce_long": 3292547,
  "poi_client_opt_idx_pe_long": 2201108,
  "poi_client_opt_idx_ce_short": 3265815,
  "poi_client_opt_idx_pe_short": 2732477,
  "poi_client_total_long": 12398183,
  "poi_client_total_short": 9224746,
  "poi_client_total_net": 3173437,
  "poi_pro_fut_idx_long": 54980,
  "poi_pro_fut_idx_short": 44849,
  "poi_pro_fut_idx_net": 10131,
  "poi_pro_fut_stk_long": 932953,
  "poi_pro_fut_stk_short": 420859,
  "poi_pro_fut_stk_net": 512094,
  "poi_pro_opt_idx_ce_long": 1298514,
  "poi_pro_opt_idx_pe_long": 1166888,
  "poi_pro_opt_idx_ce_short": 1328090,
  "poi_pro_opt_idx_pe_short": 992559,
  "poi_pro_total_long": 5965983,
  "poi_pro_total_short": 5814426,
  "poi_pro_total_net": 151557,
  "pvol_fii_fut_idx_long": 27112,
  "pvol_fii_fut_idx_short": 18353,
  "pvol_fii_fut_idx_net": 8759,
  "pvol_fii_fut_stk_long": 444571,
  "pvol_fii_fut_stk_short": 435624,
  "pvol_fii_fut_stk_net": 8947,
  "pvol_fii_opt_idx_ce_long": 5642047,
  "pvol_fii_opt_idx_pe_long": 5849224,
  "pvol_fii_opt_idx_ce_short": 5588192,
  "pvol_fii_opt_idx_pe_short": 5801359,
  "pvol_fii_total_long": 12639934,
  "pvol_fii_total_short": 12523259,
  "pvol_fii_total_net": 116675,
  "pvol_dii_fut_idx_long": 1012,
  "pvol_dii_fut_idx_short": 564,
  "pvol_dii_fut_idx_net": 448,
  "pvol_dii_fut_stk_long": 113050,
  "pvol_dii_fut_stk_short": 125422,
  "pvol_dii_fut_stk_net": -12372,
  "pvol_dii_opt_idx_ce_long": 0,
  "pvol_dii_opt_idx_pe_long": 11100,
  "pvol_dii_opt_idx_ce_short": 10655,
  "pvol_dii_opt_idx_pe_short": 0,
  "pvol_dii_total_long": 139657,
  "pvol_dii_total_short": 152027,
  "pvol_dii_total_net": -12370,
  "pvol_client_fut_idx_long": 75945,
  "pvol_client_fut_idx_short": 75085,
  "pvol_client_fut_idx_net": 860,
  "pvol_client_fut_stk_long": 453425,
  "pvol_client_fut_stk_short": 438135,
  "pvol_client_fut_stk_net": 15290,
  "pvol_client_opt_idx_ce_long": 29413289,
  "pvol_client_opt_idx_pe_long": 28569950,
  "pvol_client_opt_idx_ce_short": 29472667,
  "pvol_client_opt_idx_pe_short": 28670239,
  "pvol_client_total_long": 61537373,
  "pvol_client_total_short": 61645107,
  "pvol_client_total_net": -107734,
  "pvol_pro_fut_idx_long": 44509,
  "pvol_pro_fut_idx_short": 54576,
  "pvol_pro_fut_idx_net": -10067,
  "pvol_pro_fut_stk_long": 682835,
  "pvol_pro_fut_stk_short": 694700,
  "pvol_pro_fut_stk_net": -11865,
  "pvol_pro_opt_idx_ce_long": 43903916,
  "pvol_pro_opt_idx_pe_long": 41699489,
  "pvol_pro_opt_idx_ce_short": 43887738,
  "pvol_pro_opt_idx_pe_short": 41658165,
  "pvol_pro_total_long": 92895263,
  "pvol_pro_total_short": 92891834,
  "pvol_pro_total_net": 3429,
  "fii_stats_idx_fut_buy_contracts": 27112,
  "fii_stats_idx_fut_buy_crore": 4664.82,
  "fii_stats_idx_fut_sell_contracts": 18353,
  "fii_stats_idx_fut_sell_crore": 3139.76,
  "fii_stats_idx_fut_net_contracts": 8759,
  "fii_stats_idx_fut_net_crore": 1525.0599999999995,
  "fii_stats_idx_fut_eod_oi_contracts": 234003,
  "fii_stats_idx_fut_eod_oi_crore": 39404.98,
  "fii_stats_idx_opt_buy_contracts": 11491271,
  "fii_stats_idx_opt_buy_crore": 1931265.93,
  "fii_stats_idx_opt_sell_contracts": 11389551,
  "fii_stats_idx_opt_sell_crore": 1914092.99,
  "fii_stats_idx_opt_net_contracts": 101720,
  "fii_stats_idx_opt_net_crore": 17172.939999999944,
  "fii_stats_idx_opt_eod_oi_contracts": 2663076,
  "fii_stats_idx_opt_eod_oi_crore": 447789.18,
  "fii_stats_stk_fut_buy_contracts": 444571,
  "fii_stats_stk_fut_buy_crore": 31160.53,
  "fii_stats_stk_fut_sell_contracts": 435624,
  "fii_stats_stk_fut_sell_crore": 30875.59,
  "fii_stats_stk_fut_net_contracts": 8947,
  "fii_stats_stk_fut_net_crore": 284.9399999999987,
  "fii_stats_stk_fut_eod_oi_contracts": 6223393,
  "fii_stats_stk_fut_eod_oi_crore": 420361.12,
  "fii_stats_stk_opt_buy_contracts": 676980,
  "fii_stats_stk_opt_buy_crore": 48982.46,
  "fii_stats_stk_opt_sell_contracts": 679731,
  "fii_stats_stk_opt_sell_crore": 48964.92,
  "fii_stats_stk_opt_net_contracts": -2751,
  "fii_stats_stk_opt_net_crore": 17.540000000000873,
  "fii_stats_stk_opt_eod_oi_contracts": 782851,
  "fii_stats_stk_opt_eod_oi_crore": 53727.71,
  "fii_stats_bn_fut_buy_contracts": 9043,
  "fii_stats_bn_fut_buy_crore": 1633.41,
  "fii_stats_bn_fut_sell_contracts": 4902,
  "fii_stats_bn_fut_sell_crore": 884.71,
  "fii_stats_bn_fut_net_contracts": 4141,
  "fii_stats_bn_fut_net_crore": 748.7,
  "fii_stats_bn_fut_eod_oi_contracts": 20798,
  "fii_stats_bn_fut_eod_oi_crore": 3759.1,
  "fii_stats_bn_opt_buy_contracts": 245448,
  "fii_stats_bn_opt_buy_crore": 44274.38,
  "fii_stats_bn_opt_sell_contracts": 242475,
  "fii_stats_bn_opt_sell_crore": 43738.27,
  "fii_stats_bn_opt_net_contracts": 2973,
  "fii_stats_bn_opt_net_crore": 536.1100000000006,
  "fii_stats_bn_opt_eod_oi_contracts": 240740,
  "fii_stats_bn_opt_eod_oi_crore": 43401.89,
  "fii_stats_ni_fut_buy_contracts": 16667,
  "fii_stats_ni_fut_buy_crore": 2799.46,
  "fii_stats_ni_fut_sell_contracts": 12013,
  "fii_stats_ni_fut_sell_crore": 2017.46,
  "fii_stats_ni_fut_net_contracts": 4654,
  "fii_stats_ni_fut_net_crore": 782.0,
  "fii_stats_ni_fut_eod_oi_contracts": 190613,
  "fii_stats_ni_fut_eod_oi_crore": 31924.98,
  "fii_stats_ni_opt_buy_contracts": 11164544,
  "fii_stats_ni_opt_buy_crore": 1873512.5,
  "fii_stats_ni_opt_sell_contracts": 11062975,
  "fii_stats_ni_opt_sell_crore": 1856408.49,
  "fii_stats_ni_opt_net_contracts": 101569,
  "fii_stats_ni_opt_net_crore": 17104.01000000001,
  "fii_stats_ni_opt_eod_oi_contracts": 2353224,
  "fii_stats_ni_opt_eod_oi_crore": 393019.58,
  "nifty_volt_d": 0.00718311,
  "nifty_volt_annual": 0.13723305,
  "nifty_volt_spot_d": 0.00718311,
  "nifty_volt_fut_d": 0.00716033,
  "nifty_volt_log_ret_spot": 0.00111955,
  "nifty_volt_log_ret_fut": 0.00126286,
  "banknifty_volt_d": 0.0080774,
  "banknifty_volt_annual": 0.15431849,
  "banknifty_volt_spot_d": 0.0080774,
  "banknifty_volt_fut_d": 0.00782696,
  "banknifty_volt_log_ret_spot": 0.00860667,
  "banknifty_volt_log_ret_fut": 0.00689813,
  "deleq_universe_notional": 31599263273,
  "deleq_universe_fut_eq": 17634878905.593246,
  "mkt_idx_fut_contracts": 148578,
  "mkt_idx_fut_crore": 25416.32,
  "mkt_idx_opt_contracts": 155089015,
  "mkt_idx_opt_crore": 26092397.84,
  "mkt_stk_fut_contracts": 1693881,
  "mkt_stk_fut_crore": 120205.27,
  "mkt_stk_opt_contracts": 10280753,
  "mkt_stk_opt_crore": 752419.84,
  "mkt_fno_total_contracts": 167212227,
  "mkt_fno_total_crore": 26990439.27,
  "nifty_fut_idx_mkt_contracts": 104640,
  "nifty_fut_idx_mkt_qty": 6801600,
  "nifty_fut_idx_mkt_crore": 17584.19,
  "nifty_fut_idx_mkt_oi": 18969405,
  "banknifty_fut_idx_mkt_contracts": 37274,
  "banknifty_fut_idx_mkt_qty": 1118220,
  "banknifty_fut_idx_mkt_crore": 6728.71,
  "banknifty_fut_idx_mkt_oi": 1490070,
  "nifty_opt_idx_mkt_contracts": 150947908,
  "nifty_opt_idx_mkt_crore": 25352521.02,
  "nifty_opt_idx_mkt_oi": 537306645,
  "banknifty_opt_idx_mkt_contracts": 3583602,
  "banknifty_opt_idx_mkt_crore": 647293.87,
  "banknifty_opt_idx_mkt_oi": 32391905,
  "sec_ban_count": 2,
  "sec_ban_symbols": [
    "SAIL",
    "SAMMAANCAP"
  ],
  "irf_fii_long_excl_lt": 0.0,
  "irf_fii_long_lt": 0.0,
  "irf_fii_long_total": 0.0,
  "fpi_long_cr": 0.0,
  "fpi_permissible": 5000.0,
  "fpi_available": 5000.0,
  "fpi_pct_used": 0.0,
  "fpi_breach_90": "No",
  "cd_usdinr_near_settle": 90.6497,
  "cd_usdinr_near_expiry": "2026-01-16",
  "cd_usdinr_vol_d_pct": 0.241314,
  "cd_usdinr_vol_annual_pct": 4.610291
}