{
  "trade_date": "2026-03-23",
  "schema_version": 1,
  "skipped_fetch": [],
  "nifty_spot": 22512.65,
  "nifty_atm_strike": 22500,
  "nifty_max_pain": 22750.0,
  "nifty_max_pain_dev_pct": 1.0542961401700757,
  "nifty_ce_oi_total": 156405340,
  "nifty_pe_oi_total": 109168280,
  "nifty_ce_oi_chg": 19287190,
  "nifty_pe_oi_chg": 1157195,
  "nifty_pcr_oi": 0.6979830739794434,
  "nifty_pcr_vol": 1.0333256992676068,
  "nifty_ce_vol_total": 53457753,
  "nifty_pe_vol_total": 55239270,
  "nifty_atm_ce_oi": 3758430,
  "nifty_atm_pe_oi": 5516745,
  "nifty_max_ce_oi_strike": 24000,
  "nifty_max_pe_oi_strike": 21000,
  "nifty_atm_straddle": 398.2,
  "nifty_front_expiry": "2026-03-24",
  "banknifty_spot": 51437.75,
  "banknifty_atm_strike": 51400,
  "banknifty_max_pain": 55100.0,
  "banknifty_max_pain_dev_pct": 7.119770985317205,
  "banknifty_ce_oi_total": 19727685,
  "banknifty_pe_oi_total": 14460780,
  "banknifty_ce_oi_chg": 693045,
  "banknifty_pe_oi_chg": -674160,
  "banknifty_pcr_oi": 0.733019611779081,
  "banknifty_pcr_vol": 0.909497545270738,
  "banknifty_ce_vol_total": 2075789,
  "banknifty_pe_vol_total": 1887925,
  "banknifty_atm_ce_oi": 56220,
  "banknifty_atm_pe_oi": 53370,
  "banknifty_max_ce_oi_strike": 59000,
  "banknifty_max_pe_oi_strike": 59000,
  "banknifty_atm_straddle": 2182.3500000000004,
  "banknifty_front_expiry": "2026-03-30",
  "poi_fii_fut_idx_long": 51014,
  "poi_fii_fut_idx_short": 294975,
  "poi_fii_fut_idx_net": -243961,
  "poi_fii_fut_stk_long": 4142574,
  "poi_fii_fut_stk_short": 3139881,
  "poi_fii_fut_stk_net": 1002693,
  "poi_fii_opt_idx_ce_long": 733467,
  "poi_fii_opt_idx_pe_long": 1064583,
  "poi_fii_opt_idx_ce_short": 988342,
  "poi_fii_opt_idx_pe_short": 625313,
  "poi_fii_total_long": 6582324,
  "poi_fii_total_short": 5676553,
  "poi_fii_total_net": 905771,
  "poi_dii_fut_idx_long": 79197,
  "poi_dii_fut_idx_short": 17385,
  "poi_dii_fut_idx_net": 61812,
  "poi_dii_fut_stk_long": 388341,
  "poi_dii_fut_stk_short": 4349972,
  "poi_dii_fut_stk_net": -3961631,
  "poi_dii_opt_idx_ce_long": 3424,
  "poi_dii_opt_idx_pe_long": 32004,
  "poi_dii_opt_idx_ce_short": 956,
  "poi_dii_opt_idx_pe_short": 0,
  "poi_dii_total_long": 538545,
  "poi_dii_total_short": 4924314,
  "poi_dii_total_net": -4385769,
  "poi_client_fut_idx_long": 284282,
  "poi_client_fut_idx_short": 134482,
  "poi_client_fut_idx_net": 149800,
  "poi_client_fut_stk_long": 2815592,
  "poi_client_fut_stk_short": 335622,
  "poi_client_fut_stk_net": 2479970,
  "poi_client_opt_idx_ce_long": 3345970,
  "poi_client_opt_idx_pe_long": 2281686,
  "poi_client_opt_idx_ce_short": 2948864,
  "poi_client_opt_idx_pe_short": 2811452,
  "poi_client_total_long": 11981263,
  "poi_client_total_short": 8374261,
  "poi_client_total_net": 3607002,
  "poi_pro_fut_idx_long": 81637,
  "poi_pro_fut_idx_short": 49288,
  "poi_pro_fut_idx_net": 32349,
  "poi_pro_fut_stk_long": 1041624,
  "poi_pro_fut_stk_short": 562656,
  "poi_pro_fut_stk_net": 478968,
  "poi_pro_opt_idx_ce_long": 1376478,
  "poi_pro_opt_idx_pe_long": 1139331,
  "poi_pro_opt_idx_ce_short": 1521176,
  "poi_pro_opt_idx_pe_short": 1080839,
  "poi_pro_total_long": 6148182,
  "poi_pro_total_short": 6275185,
  "poi_pro_total_net": -127003,
  "pvol_fii_fut_idx_long": 44340,
  "pvol_fii_fut_idx_short": 53793,
  "pvol_fii_fut_idx_net": -9453,
  "pvol_fii_fut_stk_long": 499860,
  "pvol_fii_fut_stk_short": 499475,
  "pvol_fii_fut_stk_net": 385,
  "pvol_fii_opt_idx_ce_long": 4834869,
  "pvol_fii_opt_idx_pe_long": 4315466,
  "pvol_fii_opt_idx_ce_short": 4841524,
  "pvol_fii_opt_idx_pe_short": 4315892,
  "pvol_fii_total_long": 10175624,
  "pvol_fii_total_short": 10206839,
  "pvol_fii_total_net": -31215,
  "pvol_dii_fut_idx_long": 12296,
  "pvol_dii_fut_idx_short": 135,
  "pvol_dii_fut_idx_net": 12161,
  "pvol_dii_fut_stk_long": 240268,
  "pvol_dii_fut_stk_short": 214658,
  "pvol_dii_fut_stk_net": 25610,
  "pvol_dii_opt_idx_ce_long": 1086,
  "pvol_dii_opt_idx_pe_long": 604,
  "pvol_dii_opt_idx_ce_short": 1031,
  "pvol_dii_opt_idx_pe_short": 0,
  "pvol_dii_total_long": 324565,
  "pvol_dii_total_short": 287762,
  "pvol_dii_total_net": 36803,
  "pvol_client_fut_idx_long": 122269,
  "pvol_client_fut_idx_short": 120415,
  "pvol_client_fut_idx_net": 1854,
  "pvol_client_fut_stk_long": 483037,
  "pvol_client_fut_stk_short": 530667,
  "pvol_client_fut_stk_net": -47630,
  "pvol_client_opt_idx_ce_long": 21047633,
  "pvol_client_opt_idx_pe_long": 25659087,
  "pvol_client_opt_idx_ce_short": 20998081,
  "pvol_client_opt_idx_pe_short": 25627819,
  "pvol_client_total_long": 49932405,
  "pvol_client_total_short": 49797587,
  "pvol_client_total_net": 134818,
  "pvol_pro_fut_idx_long": 84367,
  "pvol_pro_fut_idx_short": 88929,
  "pvol_pro_fut_idx_net": -4562,
  "pvol_pro_fut_stk_long": 790990,
  "pvol_pro_fut_stk_short": 769355,
  "pvol_pro_fut_stk_net": 21635,
  "pvol_pro_opt_idx_ce_long": 33989318,
  "pvol_pro_opt_idx_pe_long": 31187693,
  "pvol_pro_opt_idx_ce_short": 34032270,
  "pvol_pro_opt_idx_pe_short": 31219139,
  "pvol_pro_total_long": 72188836,
  "pvol_pro_total_short": 72329242,
  "pvol_pro_total_net": -140406,
  "fii_stats_idx_fut_buy_contracts": 44340,
  "fii_stats_idx_fut_buy_crore": 6607.18,
  "fii_stats_idx_fut_sell_contracts": 53793,
  "fii_stats_idx_fut_sell_crore": 8027.31,
  "fii_stats_idx_fut_net_contracts": -9453,
  "fii_stats_idx_fut_net_crore": -1420.13,
  "fii_stats_idx_fut_eod_oi_contracts": 345989,
  "fii_stats_idx_fut_eod_oi_crore": 51138.3,
  "fii_stats_idx_opt_buy_contracts": 9150335,
  "fii_stats_idx_opt_buy_crore": 1368427.42,
  "fii_stats_idx_opt_sell_contracts": 9157416,
  "fii_stats_idx_opt_sell_crore": 1369058.9,
  "fii_stats_idx_opt_net_contracts": -7081,
  "fii_stats_idx_opt_net_crore": -631.4799999999814,
  "fii_stats_idx_opt_eod_oi_contracts": 3411705,
  "fii_stats_idx_opt_eod_oi_crore": 504058.19,
  "fii_stats_stk_fut_buy_contracts": 499860,
  "fii_stats_stk_fut_buy_crore": 29454.42,
  "fii_stats_stk_fut_sell_contracts": 499475,
  "fii_stats_stk_fut_sell_crore": 29351.44,
  "fii_stats_stk_fut_net_contracts": 385,
  "fii_stats_stk_fut_net_crore": 102.97999999999956,
  "fii_stats_stk_fut_eod_oi_contracts": 7282455,
  "fii_stats_stk_fut_eod_oi_crore": 422314.41,
  "fii_stats_stk_opt_buy_contracts": 481089,
  "fii_stats_stk_opt_buy_crore": 30101.67,
  "fii_stats_stk_opt_sell_contracts": 496155,
  "fii_stats_stk_opt_sell_crore": 31071.86,
  "fii_stats_stk_opt_net_contracts": -15066,
  "fii_stats_stk_opt_net_crore": -970.1900000000023,
  "fii_stats_stk_opt_eod_oi_contracts": 1218729,
  "fii_stats_stk_opt_eod_oi_crore": 73500.38,
  "fii_stats_bn_fut_buy_contracts": 10280,
  "fii_stats_bn_fut_buy_crore": 1604.05,
  "fii_stats_bn_fut_sell_contracts": 12496,
  "fii_stats_bn_fut_sell_crore": 1952.12,
  "fii_stats_bn_fut_net_contracts": -2216,
  "fii_stats_bn_fut_net_crore": -348.06999999999994,
  "fii_stats_bn_fut_eod_oi_contracts": 53570,
  "fii_stats_bn_fut_eod_oi_crore": 8297.46,
  "fii_stats_bn_opt_buy_contracts": 527000,
  "fii_stats_bn_opt_buy_crore": 85330.15,
  "fii_stats_bn_opt_sell_contracts": 523965,
  "fii_stats_bn_opt_sell_crore": 84888.4,
  "fii_stats_bn_opt_net_contracts": 3035,
  "fii_stats_bn_opt_net_crore": 441.75,
  "fii_stats_bn_opt_eod_oi_contracts": 609035,
  "fii_stats_bn_opt_eod_oi_crore": 93982.09,
  "fii_stats_ni_fut_buy_contracts": 29466,
  "fii_stats_ni_fut_buy_crore": 4330.26,
  "fii_stats_ni_fut_sell_contracts": 38305,
  "fii_stats_ni_fut_sell_crore": 5635.85,
  "fii_stats_ni_fut_net_contracts": -8839,
  "fii_stats_ni_fut_net_crore": -1305.5900000000001,
  "fii_stats_ni_fut_eod_oi_contracts": 260506,
  "fii_stats_ni_fut_eod_oi_crore": 38175.57,
  "fii_stats_ni_opt_buy_contracts": 8536622,
  "fii_stats_ni_opt_buy_crore": 1270126.37,
  "fii_stats_ni_opt_sell_contracts": 8548514,
  "fii_stats_ni_opt_sell_crore": 1271453.31,
  "fii_stats_ni_opt_net_contracts": -11892,
  "fii_stats_ni_opt_net_crore": -1326.9399999999441,
  "fii_stats_ni_opt_eod_oi_contracts": 2733550,
  "fii_stats_ni_opt_eod_oi_crore": 400006.51,
  "nifty_volt_d": 0.00848075,
  "nifty_volt_annual": 0.16202456,
  "nifty_volt_spot_d": 0.00843447,
  "nifty_volt_fut_d": 0.00848075,
  "nifty_volt_log_ret_spot": -0.02638275,
  "nifty_volt_log_ret_fut": -0.02740702,
  "banknifty_volt_d": 0.00964715,
  "banknifty_volt_annual": 0.18430859,
  "banknifty_volt_spot_d": 0.00964715,
  "banknifty_volt_fut_d": 0.00950704,
  "banknifty_volt_log_ret_spot": -0.03794483,
  "banknifty_volt_log_ret_fut": -0.03919009,
  "deleq_universe_notional": 30215839926,
  "deleq_universe_fut_eq": 17401993094.98604,
  "mkt_idx_fut_contracts": 263272,
  "mkt_idx_fut_crore": 39290.25,
  "mkt_idx_opt_contracts": 121035756,
  "mkt_idx_opt_crore": 18025173.87,
  "mkt_stk_fut_contracts": 2014155,
  "mkt_stk_fut_crore": 118758.55,
  "mkt_stk_opt_contracts": 9308247,
  "mkt_stk_opt_crore": 582870.79,
  "mkt_fno_total_contracts": 132621430,
  "mkt_fno_total_crore": 18766093.46,
  "nifty_fut_idx_mkt_contracts": 189147,
  "nifty_fut_idx_mkt_qty": 12294555,
  "nifty_fut_idx_mkt_crore": 27836.41,
  "nifty_fut_idx_mkt_oi": 23741705,
  "banknifty_fut_idx_mkt_contracts": 61435,
  "banknifty_fut_idx_mkt_qty": 1843050,
  "banknifty_fut_idx_mkt_crore": 9589.57,
  "banknifty_fut_idx_mkt_oi": 3333000,
  "nifty_opt_idx_mkt_contracts": 116356178,
  "nifty_opt_idx_mkt_crore": 17274570.72,
  "nifty_opt_idx_mkt_oi": 541351165,
  "banknifty_opt_idx_mkt_contracts": 4221378,
  "banknifty_opt_idx_mkt_crore": 681593.61,
  "banknifty_opt_idx_mkt_oi": 44060025,
  "sec_ban_count": 2,
  "sec_ban_symbols": [
    "SAIL",
    "SAMMAANCAP"
  ],
  "irf_fii_long_excl_lt": 0.0,
  "irf_fii_long_lt": 0.0,
  "irf_fii_long_total": 0.0,
  "fpi_long_cr": 0.0,
  "fpi_permissible": 5000.0,
  "fpi_available": 5000.0,
  "fpi_pct_used": 0.0,
  "fpi_breach_90": "No",
  "cd_usdinr_near_settle": 93.5625,
  "cd_usdinr_near_expiry": "2026-03-25",
  "cd_usdinr_vol_d_pct": 0.274833,
  "cd_usdinr_vol_annual_pct": 5.250684
}