{
  "trade_date": "2026-02-25",
  "schema_version": 1,
  "skipped_fetch": [],
  "nifty_spot": 25482.5,
  "nifty_atm_strike": 25500,
  "nifty_max_pain": 25500.0,
  "nifty_max_pain_dev_pct": 0.06867458059452565,
  "nifty_ce_oi_total": 133489265,
  "nifty_pe_oi_total": 87285705,
  "nifty_ce_oi_chg": 48426235,
  "nifty_pe_oi_chg": 36152740,
  "nifty_pcr_oi": 0.6538780852527729,
  "nifty_pcr_vol": 1.000224227730916,
  "nifty_ce_vol_total": 32489291,
  "nifty_pe_vol_total": 32496576,
  "nifty_atm_ce_oi": 7344155,
  "nifty_atm_pe_oi": 6034535,
  "nifty_max_ce_oi_strike": 25600,
  "nifty_max_pe_oi_strike": 25500,
  "nifty_atm_straddle": 294.55,
  "nifty_front_expiry": "2026-03-02",
  "banknifty_spot": 61043.35,
  "banknifty_atm_strike": 61000,
  "banknifty_max_pain": 61000.0,
  "banknifty_max_pain_dev_pct": -0.07101510647760738,
  "banknifty_ce_oi_total": 8557130,
  "banknifty_pe_oi_total": 9247170,
  "banknifty_ce_oi_chg": 2057320,
  "banknifty_pe_oi_chg": 1454280,
  "banknifty_pcr_oi": 1.0806391862692282,
  "banknifty_pcr_vol": 1.107773593471355,
  "banknifty_ce_vol_total": 828227,
  "banknifty_pe_vol_total": 917488,
  "banknifty_atm_ce_oi": 1389480,
  "banknifty_atm_pe_oi": 1597290,
  "banknifty_max_ce_oi_strike": 61000,
  "banknifty_max_pe_oi_strike": 61000,
  "banknifty_atm_straddle": 1746.25,
  "banknifty_front_expiry": "2026-03-30",
  "poi_fii_fut_idx_long": 37982,
  "poi_fii_fut_idx_short": 142463,
  "poi_fii_fut_idx_net": -104481,
  "poi_fii_fut_stk_long": 3931889,
  "poi_fii_fut_stk_short": 2682197,
  "poi_fii_fut_stk_net": 1249692,
  "poi_fii_opt_idx_ce_long": 411347,
  "poi_fii_opt_idx_pe_long": 659292,
  "poi_fii_opt_idx_ce_short": 479995,
  "poi_fii_opt_idx_pe_short": 366800,
  "poi_fii_total_long": 5150251,
  "poi_fii_total_short": 3780562,
  "poi_fii_total_net": 1369689,
  "poi_dii_fut_idx_long": 97028,
  "poi_dii_fut_idx_short": 45293,
  "poi_dii_fut_idx_net": 51735,
  "poi_dii_fut_stk_long": 159424,
  "poi_dii_fut_stk_short": 4228320,
  "poi_dii_fut_stk_net": -4068896,
  "poi_dii_opt_idx_ce_long": 1045,
  "poi_dii_opt_idx_pe_long": 52687,
  "poi_dii_opt_idx_ce_short": 0,
  "poi_dii_opt_idx_pe_short": 0,
  "poi_dii_total_long": 336728,
  "poi_dii_total_short": 4353003,
  "poi_dii_total_net": -4016275,
  "poi_client_fut_idx_long": 139146,
  "poi_client_fut_idx_short": 66086,
  "poi_client_fut_idx_net": 73060,
  "poi_client_fut_stk_long": 2731514,
  "poi_client_fut_stk_short": 280095,
  "poi_client_fut_stk_net": 2451419,
  "poi_client_opt_idx_ce_long": 2244383,
  "poi_client_opt_idx_pe_long": 1616533,
  "poi_client_opt_idx_ce_short": 2166967,
  "poi_client_opt_idx_pe_short": 1981903,
  "poi_client_total_long": 8408862,
  "poi_client_total_short": 5933959,
  "poi_client_total_net": 2474903,
  "poi_pro_fut_idx_long": 14050,
  "poi_pro_fut_idx_short": 34364,
  "poi_pro_fut_idx_net": -20314,
  "poi_pro_fut_stk_long": 656076,
  "poi_pro_fut_stk_short": 288291,
  "poi_pro_fut_stk_net": 367785,
  "poi_pro_opt_idx_ce_long": 786091,
  "poi_pro_opt_idx_pe_long": 766075,
  "poi_pro_opt_idx_ce_short": 795903,
  "poi_pro_opt_idx_pe_short": 745883,
  "poi_pro_total_long": 3370228,
  "poi_pro_total_short": 3198545,
  "poi_pro_total_net": 171683,
  "pvol_fii_fut_idx_long": 15123,
  "pvol_fii_fut_idx_short": 13533,
  "pvol_fii_fut_idx_net": 1590,
  "pvol_fii_fut_stk_long": 325075,
  "pvol_fii_fut_stk_short": 309734,
  "pvol_fii_fut_stk_net": 15341,
  "pvol_fii_opt_idx_ce_long": 2999352,
  "pvol_fii_opt_idx_pe_long": 3358205,
  "pvol_fii_opt_idx_ce_short": 3007629,
  "pvol_fii_opt_idx_pe_short": 3373985,
  "pvol_fii_total_long": 6962852,
  "pvol_fii_total_short": 6970244,
  "pvol_fii_total_net": -7392,
  "pvol_dii_fut_idx_long": 26,
  "pvol_dii_fut_idx_short": 4251,
  "pvol_dii_fut_idx_net": -4225,
  "pvol_dii_fut_stk_long": 60514,
  "pvol_dii_fut_stk_short": 76754,
  "pvol_dii_fut_stk_net": -16240,
  "pvol_dii_opt_idx_ce_long": 0,
  "pvol_dii_opt_idx_pe_long": 0,
  "pvol_dii_opt_idx_ce_short": 0,
  "pvol_dii_opt_idx_pe_short": 0,
  "pvol_dii_total_long": 67798,
  "pvol_dii_total_short": 113710,
  "pvol_dii_total_net": -45912,
  "pvol_client_fut_idx_long": 68233,
  "pvol_client_fut_idx_short": 73187,
  "pvol_client_fut_idx_net": -4954,
  "pvol_client_fut_stk_long": 401449,
  "pvol_client_fut_stk_short": 389323,
  "pvol_client_fut_stk_net": 12126,
  "pvol_client_opt_idx_ce_long": 14003565,
  "pvol_client_opt_idx_pe_long": 14056938,
  "pvol_client_opt_idx_ce_short": 13994485,
  "pvol_client_opt_idx_pe_short": 14068672,
  "pvol_client_total_long": 30195359,
  "pvol_client_total_short": 30150896,
  "pvol_client_total_net": 44463,
  "pvol_pro_fut_idx_long": 47203,
  "pvol_pro_fut_idx_short": 39614,
  "pvol_pro_fut_idx_net": 7589,
  "pvol_pro_fut_stk_long": 501558,
  "pvol_pro_fut_stk_short": 512785,
  "pvol_pro_fut_stk_net": -11227,
  "pvol_pro_opt_idx_ce_long": 17993684,
  "pvol_pro_opt_idx_pe_long": 17696991,
  "pvol_pro_opt_idx_ce_short": 17994487,
  "pvol_pro_opt_idx_pe_short": 17669477,
  "pvol_pro_total_long": 39639257,
  "pvol_pro_total_short": 39630416,
  "pvol_pro_total_net": 8841,
  "fii_stats_idx_fut_buy_contracts": 15123,
  "fii_stats_idx_fut_buy_crore": 2562.87,
  "fii_stats_idx_fut_sell_contracts": 13533,
  "fii_stats_idx_fut_sell_crore": 2294.69,
  "fii_stats_idx_fut_net_contracts": 1590,
  "fii_stats_idx_fut_net_crore": 268.17999999999984,
  "fii_stats_idx_fut_eod_oi_contracts": 180445,
  "fii_stats_idx_fut_eod_oi_crore": 30573.54,
  "fii_stats_idx_opt_buy_contracts": 6357557,
  "fii_stats_idx_opt_buy_crore": 1059353.91,
  "fii_stats_idx_opt_sell_contracts": 6381614,
  "fii_stats_idx_opt_sell_crore": 1063473.67,
  "fii_stats_idx_opt_net_contracts": -24057,
  "fii_stats_idx_opt_net_crore": -4119.760000000009,
  "fii_stats_idx_opt_eod_oi_contracts": 1917434,
  "fii_stats_idx_opt_eod_oi_crore": 320388.4,
  "fii_stats_stk_fut_buy_contracts": 325075,
  "fii_stats_stk_fut_buy_crore": 22065.97,
  "fii_stats_stk_fut_sell_contracts": 309734,
  "fii_stats_stk_fut_sell_crore": 20708.04,
  "fii_stats_stk_fut_net_contracts": 15341,
  "fii_stats_stk_fut_net_crore": 1357.9300000000003,
  "fii_stats_stk_fut_eod_oi_contracts": 6614086,
  "fii_stats_stk_fut_eod_oi_crore": 436194.63,
  "fii_stats_stk_opt_buy_contracts": 265097,
  "fii_stats_stk_opt_buy_crore": 18970.94,
  "fii_stats_stk_opt_sell_contracts": 265363,
  "fii_stats_stk_opt_sell_crore": 18639.78,
  "fii_stats_stk_opt_net_contracts": -266,
  "fii_stats_stk_opt_net_crore": 331.15999999999985,
  "fii_stats_stk_opt_eod_oi_contracts": 218847,
  "fii_stats_stk_opt_eod_oi_crore": 14830.65,
  "fii_stats_bn_fut_buy_contracts": 2195,
  "fii_stats_bn_fut_buy_crore": 404.52,
  "fii_stats_bn_fut_sell_contracts": 2164,
  "fii_stats_bn_fut_sell_crore": 398.8,
  "fii_stats_bn_fut_net_contracts": 31,
  "fii_stats_bn_fut_net_crore": 5.71999999999997,
  "fii_stats_bn_fut_eod_oi_contracts": 33607,
  "fii_stats_bn_fut_eod_oi_crore": 6188.49,
  "fii_stats_bn_opt_buy_contracts": 134246,
  "fii_stats_bn_opt_buy_crore": 24901.5,
  "fii_stats_bn_opt_sell_contracts": 140860,
  "fii_stats_bn_opt_sell_crore": 26126.5,
  "fii_stats_bn_opt_net_contracts": -6614,
  "fii_stats_bn_opt_net_crore": -1225.0,
  "fii_stats_bn_opt_eod_oi_contracts": 161830,
  "fii_stats_bn_opt_eod_oi_crore": 29635.97,
  "fii_stats_ni_fut_buy_contracts": 11461,
  "fii_stats_ni_fut_buy_crore": 1916.96,
  "fii_stats_ni_fut_sell_contracts": 10475,
  "fii_stats_ni_fut_sell_crore": 1749.17,
  "fii_stats_ni_fut_net_contracts": 986,
  "fii_stats_ni_fut_net_crore": 167.78999999999996,
  "fii_stats_ni_fut_eod_oi_contracts": 117177,
  "fii_stats_ni_fut_eod_oi_crore": 19526.17,
  "fii_stats_ni_opt_buy_contracts": 6179404,
  "fii_stats_ni_opt_buy_crore": 1027211.52,
  "fii_stats_ni_opt_sell_contracts": 6200011,
  "fii_stats_ni_opt_sell_crore": 1030602.21,
  "fii_stats_ni_opt_net_contracts": -20607,
  "fii_stats_ni_opt_net_crore": -3390.689999999944,
  "fii_stats_ni_opt_eod_oi_contracts": 1731483,
  "fii_stats_ni_opt_eod_oi_crore": 286796.34,
  "nifty_volt_d": 0.00750687,
  "nifty_volt_annual": 0.14341848,
  "nifty_volt_spot_d": 0.00746298,
  "nifty_volt_fut_d": 0.00750687,
  "nifty_volt_log_ret_spot": 0.00227277,
  "nifty_volt_log_ret_fut": 0.00111265,
  "banknifty_volt_d": 0.00820256,
  "banknifty_volt_annual": 0.15670961,
  "banknifty_volt_spot_d": 0.00820256,
  "banknifty_volt_fut_d": 0.00795667,
  "banknifty_volt_log_ret_spot": -6.471e-05,
  "banknifty_volt_log_ret_fut": -0.0011628,
  "deleq_universe_notional": 23247945719,
  "deleq_universe_fut_eq": 16733566676.880331,
  "mkt_idx_fut_contracts": 130585,
  "mkt_idx_fut_crore": 22287.35,
  "mkt_idx_opt_contracts": 70108735,
  "mkt_idx_opt_crore": 11723257.95,
  "mkt_stk_fut_contracts": 1288596,
  "mkt_stk_fut_crore": 86906.43,
  "mkt_stk_opt_contracts": 5337350,
  "mkt_stk_opt_crore": 375205.39,
  "mkt_fno_total_contracts": 76865266,
  "mkt_fno_total_crore": 12207657.12,
  "nifty_fut_idx_mkt_contracts": 96144,
  "nifty_fut_idx_mkt_qty": 6249360,
  "nifty_fut_idx_mkt_crore": 16068.29,
  "nifty_fut_idx_mkt_oi": 13903110,
  "banknifty_fut_idx_mkt_contracts": 27865,
  "banknifty_fut_idx_mkt_qty": 835950,
  "banknifty_fut_idx_mkt_crore": 5136.76,
  "banknifty_fut_idx_mkt_oi": 1548270,
  "nifty_opt_idx_mkt_contracts": 68135241,
  "nifty_opt_idx_mkt_crore": 11361634.030000001,
  "nifty_opt_idx_mkt_oi": 381053875,
  "banknifty_opt_idx_mkt_contracts": 1765035,
  "banknifty_opt_idx_mkt_crore": 327069.91000000003,
  "banknifty_opt_idx_mkt_oi": 18692265,
  "sec_ban_count": 1,
  "sec_ban_symbols": [
    "SAMMAANCAP"
  ],
  "irf_fii_long_excl_lt": 0.0,
  "irf_fii_long_lt": 0.0,
  "irf_fii_long_total": 0.0,
  "fpi_long_cr": 0.0,
  "fpi_permissible": 5000.0,
  "fpi_available": 5000.0,
  "fpi_pct_used": 0.0,
  "fpi_breach_90": "No",
  "cd_usdinr_near_settle": 90.9502,
  "cd_usdinr_near_expiry": "2026-02-25",
  "cd_usdinr_vol_d_pct": 0.258777,
  "cd_usdinr_vol_annual_pct": 4.943921
}