{
  "trade_date": "2026-03-20",
  "schema_version": 1,
  "skipped_fetch": [],
  "nifty_spot": 23114.5,
  "nifty_atm_strike": 23100,
  "nifty_max_pain": 23250.0,
  "nifty_max_pain_dev_pct": 0.5862121179346298,
  "nifty_ce_oi_total": 137118150,
  "nifty_pe_oi_total": 108011085,
  "nifty_ce_oi_chg": 18198570,
  "nifty_pe_oi_chg": 23568610,
  "nifty_pcr_oi": 0.7877227413001123,
  "nifty_pcr_vol": 1.027158683318383,
  "nifty_ce_vol_total": 43141819,
  "nifty_pe_vol_total": 44313494,
  "nifty_atm_ce_oi": 2522715,
  "nifty_atm_pe_oi": 3165305,
  "nifty_max_ce_oi_strike": 25000,
  "nifty_max_pe_oi_strike": 21000,
  "nifty_atm_straddle": 479.05,
  "nifty_front_expiry": "2026-03-24",
  "banknifty_spot": 53427.05,
  "banknifty_atm_strike": 53400,
  "banknifty_max_pain": 56000.0,
  "banknifty_max_pain_dev_pct": 4.815818953133285,
  "banknifty_ce_oi_total": 19034640,
  "banknifty_pe_oi_total": 15134940,
  "banknifty_ce_oi_chg": 62870,
  "banknifty_pe_oi_chg": 199865,
  "banknifty_pcr_oi": 0.7951261489578999,
  "banknifty_pcr_vol": 0.8402203386607361,
  "banknifty_ce_vol_total": 2050843,
  "banknifty_pe_vol_total": 1723160,
  "banknifty_atm_ce_oi": 73260,
  "banknifty_atm_pe_oi": 66420,
  "banknifty_max_ce_oi_strike": 59000,
  "banknifty_max_pe_oi_strike": 59000,
  "banknifty_atm_straddle": 1947.9499999999998,
  "banknifty_front_expiry": "2026-03-30",
  "poi_fii_fut_idx_long": 47246,
  "poi_fii_fut_idx_short": 281754,
  "poi_fii_fut_idx_net": -234508,
  "poi_fii_fut_stk_long": 4086039,
  "poi_fii_fut_stk_short": 3083731,
  "poi_fii_fut_stk_net": 1002308,
  "poi_fii_opt_idx_ce_long": 653690,
  "poi_fii_opt_idx_pe_long": 1053159,
  "poi_fii_opt_idx_ce_short": 901910,
  "poi_fii_opt_idx_pe_short": 613463,
  "poi_fii_total_long": 6427698,
  "poi_fii_total_short": 5490712,
  "poi_fii_total_net": 936986,
  "poi_dii_fut_idx_long": 71121,
  "poi_dii_fut_idx_short": 21470,
  "poi_dii_fut_idx_net": 49651,
  "poi_dii_fut_stk_long": 366771,
  "poi_dii_fut_stk_short": 4354012,
  "poi_dii_fut_stk_net": -3987241,
  "poi_dii_opt_idx_ce_long": 3364,
  "poi_dii_opt_idx_pe_long": 32004,
  "poi_dii_opt_idx_ce_short": 951,
  "poi_dii_opt_idx_pe_short": 604,
  "poi_dii_total_long": 509287,
  "poi_dii_total_short": 4931859,
  "poi_dii_total_net": -4422572,
  "poi_client_fut_idx_long": 280172,
  "poi_client_fut_idx_short": 132226,
  "poi_client_fut_idx_net": 147946,
  "poi_client_fut_stk_long": 2873818,
  "poi_client_fut_stk_short": 346218,
  "poi_client_fut_stk_net": 2527600,
  "poi_client_opt_idx_ce_long": 3058696,
  "poi_client_opt_idx_pe_long": 2251928,
  "poi_client_opt_idx_ce_short": 2711142,
  "poi_client_opt_idx_pe_short": 2812962,
  "poi_client_total_long": 11720495,
  "poi_client_total_short": 8248311,
  "poi_client_total_net": 3472184,
  "poi_pro_fut_idx_long": 81993,
  "poi_pro_fut_idx_short": 45082,
  "poi_pro_fut_idx_net": 36911,
  "poi_pro_fut_stk_long": 989322,
  "poi_pro_fut_stk_short": 531989,
  "poi_pro_fut_stk_net": 457333,
  "poi_pro_opt_idx_ce_long": 1130865,
  "poi_pro_opt_idx_pe_long": 1080788,
  "poi_pro_opt_idx_ce_short": 1232611,
  "poi_pro_opt_idx_pe_short": 990849,
  "poi_pro_total_long": 5720515,
  "poi_pro_total_short": 5707112,
  "poi_pro_total_net": 13403,
  "pvol_fii_fut_idx_long": 37817,
  "pvol_fii_fut_idx_short": 43373,
  "pvol_fii_fut_idx_net": -5556,
  "pvol_fii_fut_stk_long": 459601,
  "pvol_fii_fut_stk_short": 463566,
  "pvol_fii_fut_stk_net": -3965,
  "pvol_fii_opt_idx_ce_long": 3721815,
  "pvol_fii_opt_idx_pe_long": 3888371,
  "pvol_fii_opt_idx_ce_short": 3746532,
  "pvol_fii_opt_idx_pe_short": 3862717,
  "pvol_fii_total_long": 8585392,
  "pvol_fii_total_short": 8598171,
  "pvol_fii_total_net": -12779,
  "pvol_dii_fut_idx_long": 836,
  "pvol_dii_fut_idx_short": 2899,
  "pvol_dii_fut_idx_net": -2063,
  "pvol_dii_fut_stk_long": 123518,
  "pvol_dii_fut_stk_short": 148085,
  "pvol_dii_fut_stk_net": -24567,
  "pvol_dii_opt_idx_ce_long": 403,
  "pvol_dii_opt_idx_pe_long": 5200,
  "pvol_dii_opt_idx_ce_short": 183,
  "pvol_dii_opt_idx_pe_short": 0,
  "pvol_dii_total_long": 142431,
  "pvol_dii_total_short": 185070,
  "pvol_dii_total_net": -42639,
  "pvol_client_fut_idx_long": 112090,
  "pvol_client_fut_idx_short": 115440,
  "pvol_client_fut_idx_net": -3350,
  "pvol_client_fut_stk_long": 425048,
  "pvol_client_fut_stk_short": 392921,
  "pvol_client_fut_stk_net": 32127,
  "pvol_client_opt_idx_ce_long": 20258251,
  "pvol_client_opt_idx_pe_long": 20951583,
  "pvol_client_opt_idx_ce_short": 20243310,
  "pvol_client_opt_idx_pe_short": 20995645,
  "pvol_client_total_long": 44356507,
  "pvol_client_total_short": 44310460,
  "pvol_client_total_net": 46047,
  "pvol_pro_fut_idx_long": 89133,
  "pvol_pro_fut_idx_short": 78164,
  "pvol_pro_fut_idx_net": 10969,
  "pvol_pro_fut_stk_long": 677470,
  "pvol_pro_fut_stk_short": 681065,
  "pvol_pro_fut_stk_net": -3595,
  "pvol_pro_opt_idx_ce_long": 24087516,
  "pvol_pro_opt_idx_pe_long": 23673352,
  "pvol_pro_opt_idx_ce_short": 24077960,
  "pvol_pro_opt_idx_pe_short": 23660144,
  "pvol_pro_total_long": 54566015,
  "pvol_pro_total_short": 54556644,
  "pvol_pro_total_net": 9371,
  "fii_stats_idx_fut_buy_contracts": 37817,
  "fii_stats_idx_fut_buy_crore": 5823.68,
  "fii_stats_idx_fut_sell_contracts": 43373,
  "fii_stats_idx_fut_sell_crore": 6647.48,
  "fii_stats_idx_fut_net_contracts": -5556,
  "fii_stats_idx_fut_net_crore": -823.7999999999993,
  "fii_stats_idx_fut_eod_oi_contracts": 329000,
  "fii_stats_idx_fut_eod_oi_crore": 50091.45,
  "fii_stats_idx_opt_buy_contracts": 7610186,
  "fii_stats_idx_opt_buy_crore": 1157720.46,
  "fii_stats_idx_opt_sell_contracts": 7609249,
  "fii_stats_idx_opt_sell_crore": 1157946.62,
  "fii_stats_idx_opt_net_contracts": 937,
  "fii_stats_idx_opt_net_crore": -226.160000000149,
  "fii_stats_idx_opt_eod_oi_contracts": 3222222,
  "fii_stats_idx_opt_eod_oi_crore": 490198.18,
  "fii_stats_stk_fut_buy_contracts": 459601,
  "fii_stats_stk_fut_buy_crore": 28398.64,
  "fii_stats_stk_fut_sell_contracts": 463566,
  "fii_stats_stk_fut_sell_crore": 27962.66,
  "fii_stats_stk_fut_net_contracts": -3965,
  "fii_stats_stk_fut_net_crore": 435.97999999999956,
  "fii_stats_stk_fut_eod_oi_contracts": 7169770,
  "fii_stats_stk_fut_eod_oi_crore": 430540.06,
  "fii_stats_stk_opt_buy_contracts": 477788,
  "fii_stats_stk_opt_buy_crore": 30700.51,
  "fii_stats_stk_opt_sell_contracts": 481983,
  "fii_stats_stk_opt_sell_crore": 30963.09,
  "fii_stats_stk_opt_net_contracts": -4195,
  "fii_stats_stk_opt_net_crore": -262.58000000000175,
  "fii_stats_stk_opt_eod_oi_contracts": 1197419,
  "fii_stats_stk_opt_eod_oi_crore": 74719.36,
  "fii_stats_bn_fut_buy_contracts": 9636,
  "fii_stats_bn_fut_buy_crore": 1563.14,
  "fii_stats_bn_fut_sell_contracts": 8411,
  "fii_stats_bn_fut_sell_crore": 1363.99,
  "fii_stats_bn_fut_net_contracts": 1225,
  "fii_stats_bn_fut_net_crore": 199.1500000000001,
  "fii_stats_bn_fut_eod_oi_contracts": 49710,
  "fii_stats_bn_fut_eod_oi_crore": 8004.55,
  "fii_stats_bn_opt_buy_contracts": 365735,
  "fii_stats_bn_opt_buy_crore": 60357.98,
  "fii_stats_bn_opt_sell_contracts": 371039,
  "fii_stats_bn_opt_sell_crore": 61318.11,
  "fii_stats_bn_opt_net_contracts": -5304,
  "fii_stats_bn_opt_net_crore": -960.1299999999974,
  "fii_stats_bn_opt_eod_oi_contracts": 600211,
  "fii_stats_bn_opt_eod_oi_crore": 96202.54,
  "fii_stats_ni_fut_buy_contracts": 26816,
  "fii_stats_ni_fut_buy_crore": 4052.6,
  "fii_stats_ni_fut_sell_contracts": 34003,
  "fii_stats_ni_fut_sell_crore": 5137.1,
  "fii_stats_ni_fut_net_contracts": -7187,
  "fii_stats_ni_fut_net_crore": -1084.5000000000005,
  "fii_stats_ni_fut_eod_oi_contracts": 249677,
  "fii_stats_ni_fut_eod_oi_crore": 37596.48,
  "fii_stats_ni_opt_buy_contracts": 7164649,
  "fii_stats_ni_opt_buy_crore": 1085164.87,
  "fii_stats_ni_opt_sell_contracts": 7159907,
  "fii_stats_ni_opt_sell_crore": 1084659.35,
  "fii_stats_ni_opt_net_contracts": 4742,
  "fii_stats_ni_opt_net_crore": 505.5200000000186,
  "fii_stats_ni_opt_eod_oi_contracts": 2552074,
  "fii_stats_ni_opt_eod_oi_crore": 383434.5,
  "nifty_volt_d": 0.00827737,
  "nifty_volt_annual": 0.15813897,
  "nifty_volt_spot_d": 0.00824607,
  "nifty_volt_fut_d": 0.00827737,
  "nifty_volt_log_ret_spot": 0.00487244,
  "nifty_volt_log_ret_fut": 0.00371034,
  "banknifty_volt_d": 0.00928964,
  "banknifty_volt_annual": 0.17747826,
  "banknifty_volt_spot_d": 0.00928964,
  "banknifty_volt_fut_d": 0.00911683,
  "banknifty_volt_log_ret_spot": -0.00044817,
  "banknifty_volt_log_ret_fut": -0.00092574,
  "deleq_universe_notional": 29950902458,
  "deleq_universe_fut_eq": 17511185328.406742,
  "mkt_idx_fut_contracts": 239876,
  "mkt_idx_fut_crore": 36925.91,
  "mkt_idx_opt_contracts": 96586491,
  "mkt_idx_opt_crore": 14719036.17,
  "mkt_stk_fut_contracts": 1685637,
  "mkt_stk_fut_crore": 104250.67,
  "mkt_stk_opt_contracts": 9138341,
  "mkt_stk_opt_crore": 593357.69,
  "mkt_fno_total_contracts": 107650345,
  "mkt_fno_total_crore": 15453570.44,
  "nifty_fut_idx_mkt_contracts": 172251,
  "nifty_fut_idx_mkt_qty": 11196315,
  "nifty_fut_idx_mkt_crore": 26047.16,
  "nifty_fut_idx_mkt_oi": 22765015,
  "banknifty_fut_idx_mkt_contracts": 58546,
  "banknifty_fut_idx_mkt_qty": 1756380,
  "banknifty_fut_idx_mkt_crore": 9495.42,
  "banknifty_fut_idx_mkt_oi": 3239010,
  "nifty_opt_idx_mkt_contracts": 92244602,
  "nifty_opt_idx_mkt_crore": 14006326.62,
  "nifty_opt_idx_mkt_oi": 497749665,
  "banknifty_opt_idx_mkt_contracts": 3954223,
  "banknifty_opt_idx_mkt_crore": 653091.4,
  "banknifty_opt_idx_mkt_oi": 43176480,
  "sec_ban_count": 2,
  "sec_ban_symbols": [
    "SAIL",
    "SAMMAANCAP"
  ],
  "irf_fii_long_excl_lt": 0.0,
  "irf_fii_long_lt": 0.0,
  "irf_fii_long_total": 0.0,
  "fpi_long_cr": 0.0,
  "fpi_permissible": 5000.0,
  "fpi_available": 5000.0,
  "fpi_pct_used": 0.0,
  "fpi_breach_90": "No",
  "cd_usdinr_near_settle": 93.3483,
  "cd_usdinr_near_expiry": "2026-03-20",
  "cd_usdinr_vol_d_pct": 0.275488,
  "cd_usdinr_vol_annual_pct": 5.263196
}