{
  "trade_date": "2026-04-24",
  "schema_version": 1,
  "skipped_fetch": [],
  "nifty_spot": 23897.95,
  "nifty_atm_strike": 23900,
  "nifty_max_pain": 24000.0,
  "nifty_max_pain_dev_pct": 0.42702407528678926,
  "nifty_ce_oi_total": 200036980,
  "nifty_pe_oi_total": 135742555,
  "nifty_ce_oi_chg": 39259870,
  "nifty_pe_oi_chg": 1884025,
  "nifty_pcr_oi": 0.6785873042074521,
  "nifty_pcr_vol": 1.024232047503482,
  "nifty_ce_vol_total": 35510660,
  "nifty_pe_vol_total": 36371156,
  "nifty_atm_ce_oi": 4194060,
  "nifty_atm_pe_oi": 5405140,
  "nifty_max_ce_oi_strike": 25000,
  "nifty_max_pe_oi_strike": 23000,
  "nifty_atm_straddle": 348.1,
  "nifty_front_expiry": "2026-04-28",
  "banknifty_spot": 56089.75,
  "banknifty_atm_strike": 56100,
  "banknifty_max_pain": 56000.0,
  "banknifty_max_pain_dev_pct": -0.16001141028441024,
  "banknifty_ce_oi_total": 17269260,
  "banknifty_pe_oi_total": 15647100,
  "banknifty_ce_oi_chg": 297360,
  "banknifty_pe_oi_chg": 409530,
  "banknifty_pcr_oi": 0.9060666177936981,
  "banknifty_pcr_vol": 0.993293249020187,
  "banknifty_ce_vol_total": 3879822,
  "banknifty_pe_vol_total": 3853801,
  "banknifty_atm_ce_oi": 131640,
  "banknifty_atm_pe_oi": 142500,
  "banknifty_max_ce_oi_strike": 60000,
  "banknifty_max_pe_oi_strike": 54000,
  "banknifty_atm_straddle": 932.8,
  "banknifty_front_expiry": "2026-04-28",
  "poi_fii_fut_idx_long": 64025,
  "poi_fii_fut_idx_short": 268104,
  "poi_fii_fut_idx_net": -204079,
  "poi_fii_fut_stk_long": 4106561,
  "poi_fii_fut_stk_short": 3238021,
  "poi_fii_fut_stk_net": 868540,
  "poi_fii_opt_idx_ce_long": 658740,
  "poi_fii_opt_idx_pe_long": 906190,
  "poi_fii_opt_idx_ce_short": 885490,
  "poi_fii_opt_idx_pe_short": 522378,
  "poi_fii_total_long": 6265413,
  "poi_fii_total_short": 5545643,
  "poi_fii_total_net": 719770,
  "poi_dii_fut_idx_long": 82381,
  "poi_dii_fut_idx_short": 29436,
  "poi_dii_fut_idx_net": 52945,
  "poi_dii_fut_stk_long": 448251,
  "poi_dii_fut_stk_short": 4132496,
  "poi_dii_fut_stk_net": -3684245,
  "poi_dii_opt_idx_ce_long": 3287,
  "poi_dii_opt_idx_pe_long": 51709,
  "poi_dii_opt_idx_ce_short": 840,
  "poi_dii_opt_idx_pe_short": 464,
  "poi_dii_total_long": 616476,
  "poi_dii_total_short": 4576642,
  "poi_dii_total_net": -3960166,
  "poi_client_fut_idx_long": 223706,
  "poi_client_fut_idx_short": 85849,
  "poi_client_fut_idx_net": 137857,
  "poi_client_fut_stk_long": 2868654,
  "poi_client_fut_stk_short": 274913,
  "poi_client_fut_stk_net": 2593741,
  "poi_client_opt_idx_ce_long": 3167562,
  "poi_client_opt_idx_pe_long": 2037739,
  "poi_client_opt_idx_ce_short": 3002126,
  "poi_client_opt_idx_pe_short": 2771850,
  "poi_client_total_long": 11240359,
  "poi_client_total_short": 8357511,
  "poi_client_total_net": 2882848,
  "poi_pro_fut_idx_long": 60769,
  "poi_pro_fut_idx_short": 47492,
  "poi_pro_fut_idx_net": 13277,
  "poi_pro_fut_stk_long": 848199,
  "poi_pro_fut_stk_short": 626235,
  "poi_pro_fut_stk_net": 221964,
  "poi_pro_opt_idx_ce_long": 1387604,
  "poi_pro_opt_idx_pe_long": 1223176,
  "poi_pro_opt_idx_ce_short": 1328737,
  "poi_pro_opt_idx_pe_short": 924122,
  "poi_pro_total_long": 6200188,
  "poi_pro_total_short": 5842639,
  "poi_pro_total_net": 357549,
  "pvol_fii_fut_idx_long": 52806,
  "pvol_fii_fut_idx_short": 65971,
  "pvol_fii_fut_idx_net": -13165,
  "pvol_fii_fut_stk_long": 2668316,
  "pvol_fii_fut_stk_short": 2697622,
  "pvol_fii_fut_stk_net": -29306,
  "pvol_fii_opt_idx_ce_long": 2540022,
  "pvol_fii_opt_idx_pe_long": 2331539,
  "pvol_fii_opt_idx_ce_short": 2519913,
  "pvol_fii_opt_idx_pe_short": 2323197,
  "pvol_fii_total_long": 8165412,
  "pvol_fii_total_short": 8242484,
  "pvol_fii_total_net": -77072,
  "pvol_dii_fut_idx_long": 35719,
  "pvol_dii_fut_idx_short": 37892,
  "pvol_dii_fut_idx_net": -2173,
  "pvol_dii_fut_stk_long": 750486,
  "pvol_dii_fut_stk_short": 803902,
  "pvol_dii_fut_stk_net": -53416,
  "pvol_dii_opt_idx_ce_long": 25,
  "pvol_dii_opt_idx_pe_long": 602,
  "pvol_dii_opt_idx_ce_short": 645,
  "pvol_dii_opt_idx_pe_short": 2300,
  "pvol_dii_total_long": 806998,
  "pvol_dii_total_short": 866146,
  "pvol_dii_total_net": -59148,
  "pvol_client_fut_idx_long": 93289,
  "pvol_client_fut_idx_short": 82174,
  "pvol_client_fut_idx_net": 11115,
  "pvol_client_fut_stk_long": 860843,
  "pvol_client_fut_stk_short": 784165,
  "pvol_client_fut_stk_net": 76678,
  "pvol_client_opt_idx_ce_long": 17144497,
  "pvol_client_opt_idx_pe_long": 18272313,
  "pvol_client_opt_idx_ce_short": 17165171,
  "pvol_client_opt_idx_pe_short": 18344476,
  "pvol_client_total_long": 39868121,
  "pvol_client_total_short": 39790343,
  "pvol_client_total_net": 77778,
  "pvol_pro_fut_idx_long": 43848,
  "pvol_pro_fut_idx_short": 39625,
  "pvol_pro_fut_idx_net": 4223,
  "pvol_pro_fut_stk_long": 991859,
  "pvol_pro_fut_stk_short": 985815,
  "pvol_pro_fut_stk_net": 6044,
  "pvol_pro_opt_idx_ce_long": 22073634,
  "pvol_pro_opt_idx_pe_long": 21574182,
  "pvol_pro_opt_idx_ce_short": 22072449,
  "pvol_pro_opt_idx_pe_short": 21508663,
  "pvol_pro_total_long": 52518243,
  "pvol_pro_total_short": 52459801,
  "pvol_pro_total_net": 58442,
  "fii_stats_idx_fut_buy_contracts": 52806,
  "fii_stats_idx_fut_buy_crore": 8508.74,
  "fii_stats_idx_fut_sell_contracts": 65971,
  "fii_stats_idx_fut_sell_crore": 10612.52,
  "fii_stats_idx_fut_net_contracts": -13165,
  "fii_stats_idx_fut_net_crore": -2103.7800000000007,
  "fii_stats_idx_fut_eod_oi_contracts": 332129,
  "fii_stats_idx_fut_eod_oi_crore": 52804.6,
  "fii_stats_idx_opt_buy_contracts": 4871561,
  "fii_stats_idx_opt_buy_crore": 775497.41,
  "fii_stats_idx_opt_sell_contracts": 4843110,
  "fii_stats_idx_opt_sell_crore": 770086.03,
  "fii_stats_idx_opt_net_contracts": 28451,
  "fii_stats_idx_opt_net_crore": 5411.380000000005,
  "fii_stats_idx_opt_eod_oi_contracts": 2972797,
  "fii_stats_idx_opt_eod_oi_crore": 469598.08,
  "fii_stats_stk_fut_buy_contracts": 2668316,
  "fii_stats_stk_fut_buy_crore": 167437.51,
  "fii_stats_stk_fut_sell_contracts": 2697622,
  "fii_stats_stk_fut_sell_crore": 168481.94,
  "fii_stats_stk_fut_net_contracts": -29306,
  "fii_stats_stk_fut_net_crore": -1044.429999999993,
  "fii_stats_stk_fut_eod_oi_contracts": 7344582,
  "fii_stats_stk_fut_eod_oi_crore": 463187.55,
  "fii_stats_stk_opt_buy_contracts": 572729,
  "fii_stats_stk_opt_buy_crore": 37500.93,
  "fii_stats_stk_opt_sell_contracts": 635781,
  "fii_stats_stk_opt_sell_crore": 41329.02,
  "fii_stats_stk_opt_net_contracts": -63052,
  "fii_stats_stk_opt_net_crore": -3828.0899999999965,
  "fii_stats_stk_opt_eod_oi_contracts": 1161548,
  "fii_stats_stk_opt_eod_oi_crore": 76060.25,
  "fii_stats_bn_fut_buy_contracts": 12545,
  "fii_stats_bn_fut_buy_crore": 2112.52,
  "fii_stats_bn_fut_sell_contracts": 15494,
  "fii_stats_bn_fut_sell_crore": 2612.31,
  "fii_stats_bn_fut_net_contracts": -2949,
  "fii_stats_bn_fut_net_crore": -499.78999999999996,
  "fii_stats_bn_fut_eod_oi_contracts": 59133,
  "fii_stats_bn_fut_eod_oi_crore": 9990.84,
  "fii_stats_bn_opt_buy_contracts": 764536,
  "fii_stats_bn_opt_buy_crore": 129910.88,
  "fii_stats_bn_opt_sell_contracts": 773497,
  "fii_stats_bn_opt_sell_crore": 131354.38,
  "fii_stats_bn_opt_net_contracts": -8961,
  "fii_stats_bn_opt_net_crore": -1443.5,
  "fii_stats_bn_opt_eod_oi_contracts": 567263,
  "fii_stats_bn_opt_eod_oi_crore": 95452.92,
  "fii_stats_ni_fut_buy_contracts": 26450,
  "fii_stats_ni_fut_buy_crore": 4118.44,
  "fii_stats_ni_fut_sell_contracts": 37287,
  "fii_stats_ni_fut_sell_crore": 5825.93,
  "fii_stats_ni_fut_net_contracts": -10837,
  "fii_stats_ni_fut_net_crore": -1707.4900000000007,
  "fii_stats_ni_fut_eod_oi_contracts": 242615,
  "fii_stats_ni_fut_eod_oi_crore": 37793.78,
  "fii_stats_ni_opt_buy_contracts": 4007188,
  "fii_stats_ni_opt_buy_crore": 629232.65,
  "fii_stats_ni_opt_sell_contracts": 3967993,
  "fii_stats_ni_opt_sell_crore": 622079.87,
  "fii_stats_ni_opt_net_contracts": 39195,
  "fii_stats_ni_opt_net_crore": 7152.780000000028,
  "fii_stats_ni_opt_eod_oi_contracts": 2347467,
  "fii_stats_ni_opt_eod_oi_crore": 364647.75,
  "nifty_volt_d": 0.00924619,
  "nifty_volt_annual": 0.17664814,
  "nifty_volt_spot_d": 0.00918176,
  "nifty_volt_fut_d": 0.00924619,
  "nifty_volt_log_ret_spot": -0.0114457,
  "nifty_volt_log_ret_fut": -0.00999056,
  "banknifty_volt_d": 0.01114449,
  "banknifty_volt_annual": 0.21291514,
  "banknifty_volt_spot_d": 0.01114449,
  "banknifty_volt_fut_d": 0.01100326,
  "banknifty_volt_log_ret_spot": -0.00383025,
  "banknifty_volt_log_ret_fut": -0.00244512,
  "deleq_universe_notional": 28048607967,
  "deleq_universe_fut_eq": 17080058745.648296,
  "mkt_idx_fut_contracts": 225662,
  "mkt_idx_fut_crore": 35993.27,
  "mkt_idx_opt_contracts": 83936814,
  "mkt_idx_opt_crore": 13274200.21,
  "mkt_stk_fut_contracts": 5271504,
  "mkt_stk_fut_crore": 334055.96,
  "mkt_stk_opt_contracts": 11924794,
  "mkt_stk_opt_crore": 781123.17,
  "mkt_fno_total_contracts": 101358774,
  "mkt_fno_total_crore": 14425372.61,
  "nifty_fut_idx_mkt_contracts": 156646,
  "nifty_fut_idx_mkt_qty": 10181990,
  "nifty_fut_idx_mkt_crore": 24443.33,
  "nifty_fut_idx_mkt_oi": 22739145,
  "banknifty_fut_idx_mkt_contracts": 44755,
  "banknifty_fut_idx_mkt_qty": 1342650,
  "banknifty_fut_idx_mkt_crore": 7544.06,
  "banknifty_fut_idx_mkt_oi": 2511720,
  "nifty_opt_idx_mkt_contracts": 75194282,
  "nifty_opt_idx_mkt_crore": 11796887.910000002,
  "nifty_opt_idx_mkt_oi": 508347635,
  "banknifty_opt_idx_mkt_contracts": 7961731,
  "banknifty_opt_idx_mkt_crore": 1348494.2200000002,
  "banknifty_opt_idx_mkt_oi": 44448090,
  "sec_ban_count": 1,
  "sec_ban_symbols": [
    "SAIL"
  ],
  "irf_fii_long_excl_lt": 0.0,
  "irf_fii_long_lt": 0.0,
  "irf_fii_long_total": 0.0,
  "fpi_long_cr": 0.0,
  "fpi_permissible": 5000.0,
  "fpi_available": 5000.0,
  "fpi_pct_used": 0.0,
  "fpi_breach_90": "No",
  "cd_usdinr_near_settle": 94.2958,
  "cd_usdinr_near_expiry": "2026-04-24",
  "cd_usdinr_vol_d_pct": 0.294576,
  "cd_usdinr_vol_annual_pct": 5.627867
}